{
  "version": "1.0.0",
  "rarityWeights": {
    "common": 55,
    "uncommon": 30,
    "rare": 12,
    "mythic": 3
  },
  "powerups": [
    {
      "id": "reroll_1",
      "name": "+1 Commander Choice",
      "rarity": "common",
      "description": "Pick from 1 additional commander option",
      "effects": {
        "commanderQuantity": 1
      }
    },
    {
      "id": "color_restrict",
      "name": "Restrict 1 Color",
      "rarity": "common",
      "description": "Exclude one color from commander pool",
      "effects": {
        "colorFilterMode": "exclude",
        "colorFilterCount": 1
      }
    },
    {
      "id": "budget_upgrade_1pack",
      "name": "Upgrade Budget - 1 Pack",
      "rarity": "common",
      "description": "Replace budget cards with any in 1 pack",
      "effects": {
        "budgetUpgradePacks": 1
      }
    },
    {
      "id": "reroll_2",
      "name": "+2 Commander Choices",
      "rarity": "uncommon",
      "description": "Pick from 2 additional commander options",
      "effects": {
        "commanderQuantity": 2
      }
    },
    {
      "id": "color_include_1",
      "name": "Include 1 Color",
      "rarity": "uncommon",
      "description": "Pick 1 color to include in commander",
      "effects": {
        "colorFilterMode": "include",
        "colorFilterCount": 1
      }
    },
    {
      "id": "budget_upgrade_2pack",
      "name": "Upgrade Budget - 2 Packs",
      "rarity": "uncommon",
      "description": "Replace budget cards with any in 2 packs",
      "effects": {
        "budgetUpgradePacks": 2
      }
    },
    {
      "id": "extra_pack_rare",
      "name": "+1 Pack",
      "rarity": "rare",
      "description": "Start with 1 additional pack",
      "effects": {
        "packQuantity": 1
      }
    },
    {
      "id": "reroll_3",
      "name": "+3 Commander Choices",
      "rarity": "rare",
      "description": "Pick from 3 additional commander options",
      "effects": {
        "commanderQuantity": 3
      }
    },
    {
      "id": "color_include_2",
      "name": "Include 2 Colors",
      "rarity": "rare",
      "description": "Pick 2 colors to include in commander",
      "effects": {
        "colorFilterMode": "include",
        "colorFilterCount": 2
      }
    },
    {
      "id": "upgrade_bracket_3",
      "name": "Upgrade Bracket - 3",
      "rarity": "rare",
      "description": "One pack gets upgraded to bracket 3",
      "effects": {
        "bracketUpgrade": 3,
        "bracketUpgradePacks": 1
      }
    },
    {
      "id": "budget_full_expensive_1",
      "name": "Full Expensive - 1 Pack",
      "rarity": "rare",
      "description": "1 pack becomes fully expensive cards",
      "effects": {
        "fullExpensivePacks": 1
      }
    },
    {
      "id": "gamechanger_pack",
      "name": "Game Changer Pack",
      "rarity": "rare",
      "description": "Get 3 random game changer cards",
      "effects": {
        "specialPack": "gamechanger",
        "specialPackCount": 3
      }
    },
    {
      "id": "conspiracy_pack_rare",
      "name": "Conspiracy Pack - 3 Cards",
      "rarity": "rare",
      "description": "Get 3 random conspiracy cards",
      "effects": {
        "specialPack": "conspiracy",
        "specialPackCount": 3
      }
    },
    {
      "id": "banned_pack",
      "name": "Banned Pack",
      "rarity": "rare",
      "description": "Get 3 random banned cards",
      "effects": {
        "specialPack": "banned",
        "specialPackCount": 3
      }
    },
    {
      "id": "reroll_4",
      "name": "+4 Commander Choices",
      "rarity": "mythic",
      "description": "Pick from 4 additional commander options",
      "effects": {
        "commanderQuantity": 4
      }
    },
    {
      "id": "color_exact",
      "name": "Exact Color Selection",
      "rarity": "mythic",
      "description": "Pick exactly which colors in commander",
      "effects": {
        "colorFilterMode": "exact"
      }
    },
    {
      "id": "upgrade_bracket_4",
      "name": "Upgrade Bracket - 4",
      "rarity": "mythic",
      "description": "One pack gets upgraded to bracket 4",
      "effects": {
        "bracketUpgrade": 4,
        "bracketUpgradePacks": 1
      }
    },
    {
      "id": "budget_full_expensive_2",
      "name": "Full Expensive - 2 Packs",
      "rarity": "mythic",
      "description": "2 packs become fully expensive cards",
      "effects": {
        "fullExpensivePacks": 2
      }
    },
    {
      "id": "gamechanger_pack_mythic",
      "name": "Game Changer Pack - 3 Options",
      "rarity": "mythic",
      "description": "Get 3 random game changer cards",
      "effects": {
        "specialPack": "gamechanger",
        "specialPackCount": 3
      }
    },
    {
      "id": "conspiracy_pack_mythic",
      "name": "Conspiracy Pack - 10 Cards",
      "rarity": "mythic",
      "description": "Get 10 random conspiracy cards, can use 2 conspiracies",
      "effects": {
        "specialPack": "conspiracy",
        "specialPackCount": 10
      }
    },
    {
      "id": "manabase_upgrade",
      "name": "Manabase Upgrade",
      "rarity": "uncommon",
      "description": "Get expensive land pack including true duals",
      "effects": {
        "specialPack": "expensive_lands",
        "specialPackCount": 3
      }
    }
  ]
}
